pump_jinja.py
setup.py
pump_jinja.egg-info/PKG-INFO
pump_jinja.egg-info/SOURCES.txt
pump_jinja.egg-info/dependency_links.txt
pump_jinja.egg-info/requires.txt
pump_jinja.egg-info/top_level.txt