Metadata-Version: 1.0
Name: pump-jinja
Version: 0.0.3
Summary: A Pump middleware that uses the Jinja templating system to render responses.
Home-page: UNKNOWN
Author: Adeel Ahmad Khan
Author-email: adeel@adeel.ru
License: MIT
Platform: UNKNOWN
